durand/__init__.py
durand/_version.py
durand/callback_handler.py
durand/datatypes.py
durand/eds.py
durand/network.py
durand/node.py
durand/object_dictionary.py
durand/scheduler.py
durand/services/__init__.py
durand/services/emcy.py
durand/services/heartbeat.py
durand/services/lss.py
durand/services/nmt.py
durand/services/sync.py
durand/services/pdo/__init__.py
durand/services/pdo/base.py
durand/services/pdo/rpdo.py
durand/services/pdo/tpdo.py
durand/services/sdo/__init__.py
durand/services/sdo/download.py
durand/services/sdo/server.py
durand/services/sdo/upload.py
durand-0.5.0.dist-info/METADATA
durand-0.5.0.dist-info/WHEEL
durand-0.5.0.dist-info/top_level.txt
durand-0.5.0.dist-info/RECORD
